debreach/__init__.py
debreach/apps.py
debreach/context_processors.py
debreach/decorators.py
debreach/middleware.py
debreach/models.py
debreach/tests.py
debreach/utils.py
django_debreach-2.1.0.dist-info/AUTHORS.rst
django_debreach-2.1.0.dist-info/LICENSE
django_debreach-2.1.0.dist-info/METADATA
django_debreach-2.1.0.dist-info/WHEEL
django_debreach-2.1.0.dist-info/top_level.txt
django_debreach-2.1.0.dist-info/RECORD
