Metadata-Version: 2.1
Name: django-debreach
Version: 2.1.0
Summary: Adds middleware to give some added protection against the BREACH attack in Django.
Home-page: http://github.com/lpomfrey/django-debreach
Author: Luke Pomfrey
Author-email: luke@lukepomfrey.org
Maintainer: Luke Pomfrey
Maintainer-email: luke@lukepomfrey.org
License: UNKNOWN
Platform: UNKNOWN
Classifier: Development Status :: 5 - Production/Stable
Classifier: Environment :: Web Environment
Classifier: Intended Audience :: Developers
Classifier: License :: OSI Approved :: BSD License
Classifier: Operating System :: OS Independent
Classifier: Framework :: Django
Classifier: Framework :: Django :: 2.2
Classifier: Framework :: Django :: 3.2
Classifier: Framework :: Django :: 4.0
Classifier: Programming Language :: Python
Classifier: Programming Language :: Python :: 3
Classifier: Programming Language :: Python :: 3.7
Classifier: Programming Language :: Python :: 3.8
Classifier: Programming Language :: Python :: 3.9
Classifier: Programming Language :: Python :: 3.10
Classifier: Programming Language :: Python :: Implementation :: CPython
Classifier: Programming Language :: Python :: Implementation :: PyPy
Classifier: Topic :: Internet :: WWW/HTTP
Requires-Python: >=3.7
License-File: LICENSE
License-File: AUTHORS.rst
